asypinner/__init__.py
asypinner/log.py
asypinner/manager.py
asypinner/misc.py
asypinner/store.py
asypinner-0.2.1.dist-info/WHEEL
asypinner-0.2.1.dist-info/METADATA
asypinner-0.2.1.dist-info/RECORD
