Metadata-Version: 2.1
Name: asypinner
Version: 0.2.1
Summary: Async command-line spinner
License: MIT
Author: Hiroki Konishi
Author-email: relastle@gmail.com
Requires-Python: >=3.6,<4.0
Classifier: License :: OSI Approved :: MIT License
Classifier: Programming Language :: Python :: 3
Classifier: Programming Language :: Python :: 3.6
Classifier: Programming Language :: Python :: 3.7
Classifier: Programming Language :: Python :: 3.8
Requires-Dist: colorama (>=0.4.3,<0.5.0)
